{
  "type": "minecraft:chest",
  "pools": [
    {
      "name": "main",
      "rolls": 1.0,
      "entries": [
        {
          "type": "minecraft:item",
          "weight": 2,
          "name": "fusion:bronze_sword"
        },
        {
          "type": "minecraft:item",
          "weight": 2,
          "name": "fusion:bronze_axe"
        },
        {
          "type": "minecraft:item",
          "weight": 2,
          "name": "fusion:steel_sword"
        },
        {
          "type": "minecraft:item",
          "weight": 2,
          "name": "fusion:steel_axe"
        },
        {
          "type": "minecraft:item",
          "name": "fusion:thyrium_sword"
        },
        {
          "type": "minecraft:item",
          "name": "fusion:thyrium_axe"
        },
        {
          "type": "minecraft:item",
          "weight": 2,
          "functions": [
            {
              "function": "minecraft:set_count",
              "count": {
                "min": 1.0,
                "max": 3.0,
                "type": "minecraft:uniform"
              }
            }
          ],
          "name": "fusion:large_bronze_chunk"
        },
        {
          "type": "minecraft:item",
          "weight": 2,
          "functions": [
            {
              "function": "minecraft:set_count",
              "count": {
                "min": 2.0,
                "max": 4.0,
                "type": "minecraft:uniform"
              }
            }
          ],
          "name": "fusion:large_steel_chunk"
        },
        {
          "type": "minecraft:item",
          "functions": [
            {
              "function": "minecraft:set_count",
              "count": {
                "min": 1.0,
                "max": 3.0,
                "type": "minecraft:uniform"
              }
            }
          ],
          "name": "fusion:large_thyrium_chunk"
        },
        {
          "type": "minecraft:item",
          "weight": 2,
          "functions": [
            {
              "function": "minecraft:set_count",
              "count": {
                "min": 2.0,
                "max": 4.0,
                "type": "minecraft:uniform"
              }
            }
          ],
          "name": "fusion:bronze_ingot"
        },
        {
          "type": "minecraft:item",
          "weight": 2,
          "functions": [
            {
              "function": "minecraft:set_count",
              "count": {
                "min": 2.0,
                "max": 4.0,
                "type": "minecraft:uniform"
              }
            }
          ],
          "name": "fusion:steel_ingot"
        },
        {
          "type": "minecraft:item",
          "functions": [
            {
              "function": "minecraft:set_count",
              "count": {
                "min": 2.0,
                "max": 3.0,
                "type": "minecraft:uniform"
              }
            }
          ],
          "name": "fusion:thyrium_ingot"
        }
      ],
      "conditions": [
        {
          "condition": "minecraft:random_chance",
          "chance": 0.25
        }
      ]
    }
  ]
}