{
  "type": "forge:conditional",
  "recipes": [
    {
      "conditions": [
        {
          "type": "fusion:flag",
          "flag": "bronze_tools"
        }
      ],
      "recipe": {
        "type": "minecraft:crafting_shaped",
        "key": {
          "S": {
            "item": "fusion:bronze_ingot"
          },
          "T": {
            "tag": "forge:rods/wooden"
          }
        },
        "pattern": [
          "SS ",
          "ST ",
          " T "
        ],
        "result": {
          "item": "fusion:bronze_axe"
        }
      }
    }
  ]
}